odoo/addons/l10n_fi_sale_refund_payment_reference/LICENSE
odoo/addons/l10n_fi_sale_refund_payment_reference/README.rst
odoo/addons/l10n_fi_sale_refund_payment_reference/__init__.py
odoo/addons/l10n_fi_sale_refund_payment_reference/__manifest__.py
odoo/addons/l10n_fi_sale_refund_payment_reference/i18n/l10n_fi_sale_refund_payment_reference.pot
odoo/addons/l10n_fi_sale_refund_payment_reference/models/__init__.py
odoo/addons/l10n_fi_sale_refund_payment_reference/models/account_move.py
odoo/addons/l10n_fi_sale_refund_payment_reference/readme/CONTRIBUTORS.rst
odoo/addons/l10n_fi_sale_refund_payment_reference/readme/DESCRIPTION.rst
odoo/addons/l10n_fi_sale_refund_payment_reference/readme/USAGE.rst
odoo/addons/l10n_fi_sale_refund_payment_reference/static/description/icon.png
odoo/addons/l10n_fi_sale_refund_payment_reference/static/description/index.html
odoo/addons/l10n_fi_sale_refund_payment_reference/tests/__init__.py
odoo/addons/l10n_fi_sale_refund_payment_reference/tests/test_refund_reference.py
odoo13_addon_l10n_fi_sale_refund_payment_reference-13.0.1.0.1.dev3.dist-info/METADATA
odoo13_addon_l10n_fi_sale_refund_payment_reference-13.0.1.0.1.dev3.dist-info/WHEEL
odoo13_addon_l10n_fi_sale_refund_payment_reference-13.0.1.0.1.dev3.dist-info/top_level.txt
odoo13_addon_l10n_fi_sale_refund_payment_reference-13.0.1.0.1.dev3.dist-info/RECORD
